better_hooks/__init__.py
better_hooks/groups.py
better_hooks/hooks.py
better_hooks/mixins.py
better_hooks/py.typed
better_hooks/scope.py
better_hooks/stack.py
better_hooks/types.py
better_hooks/utils.py
better_hooks/context/__init__.py
better_hooks/context/manager.py
better_hooks/context/mixins.py
better_hooks/context/types.py
better_hooks-0.0.3.dist-info/METADATA
better_hooks-0.0.3.dist-info/WHEEL
better_hooks-0.0.3.dist-info/top_level.txt
better_hooks-0.0.3.dist-info/RECORD
