Metadata-Version: 2.1
Name: better-hooks
Version: 0.0.3
